collective.manifestjson-1.0b1-py3.11-nspkg.pth
collective/manifestjson/__init__.py
collective/manifestjson/configure.zcml
collective/manifestjson/interfaces.py
collective/manifestjson/permissions.zcml
collective/manifestjson/setuphandlers.py
collective/manifestjson/testing.py
collective/manifestjson/browser/__init__.py
collective/manifestjson/browser/configure.zcml
collective/manifestjson/browser/overrides/.gitkeep
collective/manifestjson/browser/static/.gitkeep
collective/manifestjson/controlpanels/__init__.py
collective/manifestjson/controlpanels/configure.zcml
collective/manifestjson/controlpanels/manifest_settings/__init__.py
collective/manifestjson/controlpanels/manifest_settings/configure.zcml
collective/manifestjson/controlpanels/manifest_settings/controlpanel.py
collective/manifestjson/locales/README.rst
collective/manifestjson/locales/__init__.py
collective/manifestjson/locales/collective.manifestjson.pot
collective/manifestjson/locales/update.py
collective/manifestjson/locales/update.sh
collective/manifestjson/locales/de/LC_MESSAGES/collective.manifestjson.po
collective/manifestjson/locales/en/LC_MESSAGES/collective.manifestjson.po
collective/manifestjson/profiles/default/browserlayer.xml
collective/manifestjson/profiles/default/catalog.xml
collective/manifestjson/profiles/default/controlpanel.xml
collective/manifestjson/profiles/default/metadata.xml
collective/manifestjson/profiles/default/rolemap.xml
collective/manifestjson/profiles/default/registry/main.xml
collective/manifestjson/profiles/default/registry/manifest_settings.xml
collective/manifestjson/profiles/uninstall/browserlayer.xml
collective/manifestjson/tests/__init__.py
collective/manifestjson/tests/test_robot.py
collective/manifestjson/tests/test_setup.py
collective/manifestjson/tests/test_view_manifest_json_view.py
collective/manifestjson/tests/test_viewlet_manifest_json_viewlet.py
collective/manifestjson/tests/robot/test_example.robot
collective/manifestjson/viewlets/__init__.py
collective.manifestjson-1.0b1.dist-info/LICENSE.GPL
collective.manifestjson-1.0b1.dist-info/LICENSE.rst
collective.manifestjson-1.0b1.dist-info/METADATA
collective.manifestjson-1.0b1.dist-info/WHEEL
collective.manifestjson-1.0b1.dist-info/entry_points.txt
collective.manifestjson-1.0b1.dist-info/namespace_packages.txt
collective.manifestjson-1.0b1.dist-info/top_level.txt
collective.manifestjson-1.0b1.dist-info/RECORD
